sseclient/__init__.py
sseclient/version.py
sseclient_py-1.7.2.dist-info/LICENSE
sseclient_py-1.7.2.dist-info/METADATA
sseclient_py-1.7.2.dist-info/WHEEL
sseclient_py-1.7.2.dist-info/pbr.json
sseclient_py-1.7.2.dist-info/top_level.txt
sseclient_py-1.7.2.dist-info/zip-safe
sseclient_py-1.7.2.dist-info/RECORD
