Metadata-Version: 1.1
Name: sseclient-py
Version: 1.7.2
Summary: SSE client for Python
Home-page: https://github.com/mpetazzoni/sseclient
Author: Maxime Petazzoni
Author-email: maxime.petazzoni@bulix.org
License: Apache Software License v2
Platform: UNKNOWN
Classifier: Operating System :: OS Independent
Classifier: Programming Language :: Python
Classifier: Programming Language :: Python :: 2
Classifier: Programming Language :: Python :: 2.7
Classifier: Programming Language :: Python :: 3
Classifier: Programming Language :: Python :: 3.5
Classifier: Programming Language :: Python :: 3.7
